dagent/DagNode.py
dagent/DecisionNode.py
dagent/FunctionNode.py
dagent/__init__.py
dagent/base_functions.py
dagent-0.0.9.dist-info/METADATA
dagent-0.0.9.dist-info/WHEEL
dagent-0.0.9.dist-info/RECORD
