Metadata-Version: 2.3
Name: dagent
Version: 0.0.9
Summary: AI Agents as DAGs - Directed Acyclic Graphs
Author-email: Parth Sareen <parth@extensible.dev>
Requires-Python: >=3.10
Requires-Dist: litellm>=1.44.19
